foursquare/__init__.py
foursquare/tests/__init__.py
foursquare/tests/_creds.example.py
foursquare/tests/_creds.py
foursquare/tests/test_checkins.py
foursquare/tests/test_events.py
foursquare/tests/test_lang.py
foursquare/tests/test_lists.py
foursquare/tests/test_multi.py
foursquare/tests/test_oauth.py
foursquare/tests/test_pages.py
foursquare/tests/test_photos.py
foursquare/tests/test_ratelimit.py
foursquare/tests/test_settings.py
foursquare/tests/test_specials.py
foursquare/tests/test_tips.py
foursquare/tests/test_users.py
foursquare/tests/test_venues.py
foursquare-1!2019.9.11.dist-info/LICENSE
foursquare-1!2019.9.11.dist-info/METADATA
foursquare-1!2019.9.11.dist-info/WHEEL
foursquare-1!2019.9.11.dist-info/top_level.txt
foursquare-1!2019.9.11.dist-info/zip-safe
foursquare-1!2019.9.11.dist-info/RECORD
