Metadata-Version: 2.1
Name: foursquare
Version: 1!2019.9.11
Summary: easy-as-pie foursquare API client
Home-page: http://github.com/mLewisLogic/foursquare
Author: Mike Lewis
Author-email: mlewis.mail@gmail.com
License: MIT License
Download-URL: http://github.com/mLewisLogic/foursquare/tarball/master
Keywords: foursquare api
Platform: UNKNOWN
Classifier: Development Status :: 5 - Production/Stable
Classifier: Intended Audience :: Developers
Classifier: Natural Language :: English
Classifier: Operating System :: OS Independent
Classifier: Programming Language :: Python
Classifier: Topic :: Internet :: WWW/HTTP :: Dynamic Content
Classifier: License :: OSI Approved :: MIT License
Requires-Dist: requests (>=2.1)
Requires-Dist: six
